Quart_Authorization_Discord/__init__.py
Quart_Authorization_Discord/base.py
Quart_Authorization_Discord/client.py
Quart_Authorization_Discord/exceptions.py
Quart_Authorization_Discord/http.py
Quart_Authorization_Discord/models/__init__.py
Quart_Authorization_Discord/models/guild.py
Quart_Authorization_Discord/models/user.py
Quart_Authorization_Discord-1.0.3.dist-info/LICENSE.txt
Quart_Authorization_Discord-1.0.3.dist-info/METADATA
Quart_Authorization_Discord-1.0.3.dist-info/WHEEL
Quart_Authorization_Discord-1.0.3.dist-info/top_level.txt
Quart_Authorization_Discord-1.0.3.dist-info/RECORD
