Metadata-Version: 2.1
Name: Quart-Authorization-Discord
Version: 1.0.3
Summary: Quart Discord Authorization Library
Home-page: UNKNOWN
Author: Tunay Ada Karacan
Author-email: tunayada@gmail.com
License: MIT
Platform: UNKNOWN
Classifier: Development Status :: 4 - Beta
Classifier: Intended Audience :: Education
Classifier: License :: OSI Approved :: MIT License
Classifier: Natural Language :: Turkish
Classifier: Operating System :: Microsoft :: Windows
Classifier: Operating System :: POSIX :: Linux
Classifier: Operating System :: MacOS
Classifier: Programming Language :: Python :: 3.8
Requires-Dist: httpx
Requires-Dist: authlib
Requires-Dist: aiohttp
Requires-Dist: quart
